.gitignore
CITATION.cff
LICENSE
README.md
requirements.txt
setup.py
dataset_preprocessing/DailyDialog/add_DDpp_annotations.py
dataset_preprocessing/DailyDialog/add_cider_annotations.py
dataset_preprocessing/DailyDialog/add_improved_annotations.py
dataset_preprocessing/DailyDialog/add_reccon_causal_emotion_annotations.py
dataset_preprocessing/DailyDialog/convert_DailyDialog.py
dataset_preprocessing/DailyDialog/download_and_convert_daily_dialogue.sh
dataset_preprocessing/DailyDialog/gather_topics.py
dataset_preprocessing/DailyDialog/generate_few_shot_data_TTiDB_ids.py
dataset_preprocessing/DailyDialog/generate_full_data_TTiDB_ids.py
dataset_preprocessing/DailyDialog/utils.py
dataset_preprocessing/MELD/convert_meld.py
dataset_preprocessing/MELD/download_and_convert_meld.sh
dataset_preprocessing/MELD/utterances_map.json
dataset_preprocessing/friends/add_dialogre_annotations.py
dataset_preprocessing/friends/add_friends_QA_annotations.py
dataset_preprocessing/friends/add_friends_personality_detection_annotations.py
dataset_preprocessing/friends/add_meld_annotations.py
dataset_preprocessing/friends/convert_emoryNLP.py
dataset_preprocessing/friends/dialogre_manual_mapping.py
dataset_preprocessing/friends/download_and_convert_friends.sh
dataset_preprocessing/friends/generate_few_shot_data_TTiDB_ids.py
dataset_preprocessing/friends/generate_full_data_TTiDB_ids.py
dataset_preprocessing/friends/map_dialogre_to_friends.py
dataset_preprocessing/friends/meld_manual_mapping.py
dataset_preprocessing/friends/utils.py
examples/results_analysis_targeted.py
tlidb/__init__.py
tlidb/version.py
tlidb.egg-info/PKG-INFO
tlidb.egg-info/SOURCES.txt
tlidb.egg-info/dependency_links.txt
tlidb.egg-info/entry_points.txt
tlidb.egg-info/requires.txt
tlidb.egg-info/top_level.txt
tlidb/TLiDB/__init__.py
tlidb/TLiDB/data_loaders/__init__.py
tlidb/TLiDB/data_loaders/data_loaders.py
tlidb/TLiDB/datasets/DailyDialog_dataset.py
tlidb/TLiDB/datasets/Friends_dataset.py
tlidb/TLiDB/datasets/TLiDB_dataset.py
tlidb/TLiDB/datasets/__init__.py
tlidb/TLiDB/datasets/clinc150_dataset.py
tlidb/TLiDB/datasets/get_dataset.py
tlidb/TLiDB/metrics/__init__.py
tlidb/TLiDB/metrics/all_metrics.py
