Metadata-Version: 2.1
Name: tlidb
Version: 1.0.3
Summary: The Transfer Learning in Dialogue Baselines Toolkit
Home-page: https://github.com/alon-albalak/TLiDB
Author: Alon Albalak
Author-email: alon_albalak@ucsb.edu
License: MIT
Platform: UNKNOWN
Classifier: Topic :: Scientific/Engineering :: Artificial Intelligence
Classifier: Intended Audience :: Science/Research
Classifier: Programming Language :: Python :: 3
Classifier: License :: OSI Approved :: MIT License
Requires-Python: >=3.6
